easy_expense_tracker/__init__.py
easy_expense_tracker/__main__.py
easy_expense_tracker/aggregator.py
easy_expense_tracker/balance.py
easy_expense_tracker/importer.py
easy_expense_tracker/reviewer.py
easy_expense_tracker/extractor/__init__.py
easy_expense_tracker/extractor/bradesco.py
easy_expense_tracker/extractor/caixa.py
easy_expense_tracker/extractor/extraction_result.py
easy_expense_tracker/extractor/itau.py
easy_expense_tracker/extractor/nubank-credit.py
easy_expense_tracker/extractor/nubank.py
easy_expense_tracker/extractor/sodexo.py
easy_expense_tracker/extractor/util.py
easy_expense_tracker-0.0.5.dist-info/METADATA
easy_expense_tracker-0.0.5.dist-info/WHEEL
easy_expense_tracker-0.0.5.dist-info/licenses/LICENSE
easy_expense_tracker-0.0.5.dist-info/RECORD
