Metadata-Version: 2.3
Name: easy_expense_tracker
Version: 0.0.5
Summary: Easy Expense Tracker is a straightforward tool designed to import and consolidate account statements from various financial services into an SQL-compatible database
Project-URL: Homepage, https://github.com/areisbr/easy_expense_tracker
Project-URL: Issues, https://github.com/areisbr/easy_expense_tracker/issues
Author-email: Alberto Reis <os@albertoreis.com.br>
License-File: LICENSE
Classifier: License :: OSI Approved :: MIT License
Classifier: Operating System :: OS Independent
Classifier: Programming Language :: Python :: 3
Requires-Python: >=3.11
Requires-Dist: sqlalchemy==2.0.22
Requires-Dist: typing-extensions==4.8.0
